syncstar/__init__.py
syncstar/auth.py
syncstar/base.py
syncstar/config/__init__.py
syncstar/config/images.yml
syncstar/config/standard.py
syncstar/dyno.py
syncstar/feed.py
syncstar/frontend/assets/index-CT6Q7wjq.js
syncstar/frontend/assets/index-jasp-4Wh.css
syncstar/frontend/assets/mono_bdit-De0BkA58.ttf
syncstar/frontend/assets/mono_bold-DirYFTCx.ttf
syncstar/frontend/assets/mono_rlar-Dh36KTnx.ttf
syncstar/frontend/assets/mono_rlit-B66cfCmv.ttf
syncstar/frontend/assets/sans_bdit-vdT15Ezk.ttf
syncstar/frontend/assets/sans_bold-DDXop4cx.ttf
syncstar/frontend/assets/sans_rlar-DOEsKK9O.ttf
syncstar/frontend/assets/sans_rlit-J5LHKyOK.ttf
syncstar/frontend/home.html
syncstar/main.py
syncstar/root.py
syncstar/system/endpoint.service
syncstar/system/worker.service
syncstar/task.py
syncstar/util.py
syncstar/view.py
syncstar-0.2.2.dist-info/LICENSE
syncstar-0.2.2.dist-info/METADATA
syncstar-0.2.2.dist-info/WHEEL
syncstar-0.2.2.dist-info/entry_points.txt
syncstar-0.2.2.dist-info/RECORD
